hdplot/__init__.py
hdplot/hdplot.py
hdplot/test.py
hdplot-0.0.0.20230516.dist-info/LICENSE
hdplot-0.0.0.20230516.dist-info/METADATA
hdplot-0.0.0.20230516.dist-info/WHEEL
hdplot-0.0.0.20230516.dist-info/top_level.txt
hdplot-0.0.0.20230516.dist-info/RECORD
