Metadata-Version: 2.1
Name: hdplot
Version: 0.0.0.20230516
Summary: HD plots
Home-page: https://github.com/physicsland/HD_dataViz
Author: Edwin Lo
Author-email: elo@regression.fit
Project-URL: Bug Tracker, https://github.com/physicsland/HD_dataViz/issues
Classifier: Programming Language :: Python :: 3
Classifier: License :: OSI Approved :: MIT License
Classifier: Operating System :: OS Independent
Requires-Python: >=3.6
License-File: LICENSE
Requires-Dist: numpy
Requires-Dist: matplotlib
Requires-Dist: pandas
